tests/__init__.py
tests/base_classes/__init__.py
tests/base_classes/test_attr.py
tests/base_classes/test_list.py
tests/base_classes/test_meta_classes.py
tests/base_classes/test_tree.py
tests/base_classes/test_trick_item.py
tests/calculate/__init__.py
tests/calculate/test_acc.py
tests/frame/__init__.py
tests/frame/test_meter.py
tests/frame/test_params.py
tests/frame/test_rndmanager.py
tests/frame/test_saver.py
tests/frame/test_trainer.py
tests/utils/__init__.py
tests/utils/test_random.py
thexp/__init__.py
thexp/globals.py
thexp/analyse/__init__.py
thexp/analyse/charts.py
thexp/analyse/constrain.py
thexp/analyse/querys.py
thexp/analyse/reader.py
thexp/analyse/viewer.py
thexp/base_classes/__init__.py
thexp/base_classes/attr.py
thexp/base_classes/defaults.py
thexp/base_classes/errors.py
thexp/base_classes/list.py
thexp/base_classes/metaclasses.py
thexp/base_classes/params_vars.py
thexp/base_classes/qnode.py
thexp/base_classes/tree.py
thexp/base_classes/trickitems.py
thexp/calculate/__init__.py
thexp/calculate/accuracy.py
thexp/calculate/memory.py
thexp/calculate/schedule.py
thexp/calculate/tensor.py
thexp/cli/__init__.py
thexp/cli/cli.py
thexp/cli/api/__init__.py
thexp/cli/api/gpu_call.py
thexp/cli/templete/arch/__init__.py-tpl
thexp/cli/templete/arch/lenet.py-tpl
thexp/cli/templete/arch/wideresnet.py-tpl
thexp/cli/templete/data/__init__.py-tpl
thexp/cli/templete/data/dataxy.py-tpl
thexp/cli/templete/data/delegate.py-tpl
thexp/cli/templete/data/transforms.py-tpl
thexp/cli/templete/trainers/__init__.py-tpl
thexp/cli/templete/trainers/example.py-tpl
thexp/cli/templete/trainers/mixin/__init__.py-tpl
thexp/cli/templete/trainers/mixin/acc.py-tpl
thexp/cli/templete/trainers/mixin/callbacks.py-tpl
thexp/cli/templete/trainers/mixin/datasets.py-tpl
thexp/cli/templete/trainers/mixin/losses.py-tpl
thexp/cli/templete/trainers/mixin/models.py-tpl
thexp/cli/templete/trainers/mixin/tricks.py-tpl
thexp/contrib/__init__.py
thexp/contrib/device.py
thexp/contrib/board/BatchEmbedding.py
thexp-1.5.1.1.dist-info/LICENSE
thexp-1.5.1.1.dist-info/METADATA
thexp-1.5.1.1.dist-info/WHEEL
thexp-1.5.1.1.dist-info/entry_points.txt
thexp-1.5.1.1.dist-info/top_level.txt
thexp-1.5.1.1.dist-info/RECORD
