Metadata-Version: 2.1
Name: thexp
Version: 1.5.1.1
Summary: An useful torch framework for dl experiments.
Home-page: https://github.com/sailist/thexp
Author: sailist
Author-email: sailist@outlook.com
License: Apache License 2.0
Keywords: thexp
Platform: UNKNOWN
Classifier: Development Status :: 3 - Alpha
Classifier: Intended Audience :: Developers
Classifier: Topic :: Software Development :: Build Tools
Classifier: License :: OSI Approved :: Apache Software License
Classifier: Programming Language :: Python :: 3
Classifier: Programming Language :: Python :: 3.5
Requires-Dist: torch
Requires-Dist: matplotlib
Requires-Dist: numpy (==1.18.0)
Requires-Dist: pandas
Requires-Dist: fire
Requires-Dist: gitpython
